colouredprinter
